ffrem/__init__.py
ffrem/ffrem.py
ffrem/transforms.py
ffrem/util.py
ff_rem-0.1.0.dist-info/AUTHORS.rst
ff_rem-0.1.0.dist-info/LICENSE
ff_rem-0.1.0.dist-info/METADATA
ff_rem-0.1.0.dist-info/WHEEL
ff_rem-0.1.0.dist-info/entry_points.txt
ff_rem-0.1.0.dist-info/top_level.txt
ff_rem-0.1.0.dist-info/RECORD
