Metadata-Version: 2.1
Name: ff-rem
Version: 0.1.0
Summary: Implementation of FF-REM for HOOMD-blue.
Home-page: https://bitbucket.org/glotzer/ff-rem
Author: Carl Simon Adorf
Author-email: csadorf@umich.edu
License: MIT license
Keywords: FF-REM
Platform: UNKNOWN
Classifier: Development Status :: 2 - Pre-Alpha
Classifier: Intended Audience :: Developers
Classifier: License :: OSI Approved :: MIT License
Classifier: Natural Language :: English
Classifier: Programming Language :: Python :: 3
Classifier: Programming Language :: Python :: 3.4
Classifier: Programming Language :: Python :: 3.5
Classifier: Programming Language :: Python :: 3.6
Classifier: Programming Language :: Python :: 3.7
Requires-Dist: Click (>=6.0)
